awscli_plugin_proxy/__init__.py
awscli_plugin_proxy-0.5.1.dist-info/LICENSE
awscli_plugin_proxy-0.5.1.dist-info/METADATA
awscli_plugin_proxy-0.5.1.dist-info/WHEEL
awscli_plugin_proxy-0.5.1.dist-info/top_level.txt
awscli_plugin_proxy-0.5.1.dist-info/RECORD
