Metadata-Version: 2.1
Name: awscli-plugin-proxy
Version: 0.5.1
Summary: Proxy plugin for AWS CLI (based on https://github.com/nowak-ninja/awscli-s3-proxy)
Home-page: https://github.com/cyralinc/awscli-plugin-proxy
Download-URL: https://codeload.github.com/cyralinc/awscli-plugin-proxy/zip/refs/heads/master
Author: Sebastian Nowak
Author-email: sebastian@nowak.ninja
Keywords: awscli,plugin,proxy
License-File: LICENSE
